dietbox/__init__.py
dietbox/version.py
dietbox/abtest/__init__.py
dietbox/abtest/stats.py
dietbox/abtest/stats_util.py
dietbox/data/__init__.py
dietbox/data/analysis/__init__.py
dietbox/data/analysis/descriptions.py
dietbox/data/extraction/__init__.py
dietbox/data/extraction/web.py
dietbox/data/sync/__init__.py
dietbox/data/sync/aws.py
dietbox/data/sync/local.py
dietbox/data/wrangling/__init__.py
dietbox/data/wrangling/datetime.py
dietbox/data/wrangling/json.py
dietbox/data/wrangling/misc.py
dietbox/lab/__init__.py
dietbox/lab/data/__init__.py
dietbox/lab/data/extraction/__init__.py
dietbox/lab/data/extraction/postgres.py
dietbox/lab/data/extraction/sql.py
dietbox/lab/model/__init__.py
dietbox/lab/model/feature.py
dietbox/texts/__init__.py
dietbox/texts/validator.py
dietbox/texts/words.py
dietbox/texts/wrangling/__init__.py
dietbox/texts/wrangling/companies.py
dietbox/texts/wrangling/consts.py
dietbox/utils/__init__.py
dietbox/utils/io.py
dietbox/utils/sugar.py
dietbox/visual/__init__.py
dietbox/visual/eda.py
dietbox-0.1.0.dist-info/LICENSE
dietbox-0.1.0.dist-info/METADATA
dietbox-0.1.0.dist-info/WHEEL
dietbox-0.1.0.dist-info/top_level.txt
dietbox-0.1.0.dist-info/RECORD
